fastapi_manage/__init__.py
fastapi_manage/main.py
fastapi_manage/redis.py
fastapi_manage-0.8.0.dist-info/entry_points.txt
fastapi_manage-0.8.0.dist-info/LICENSE
fastapi_manage-0.8.0.dist-info/WHEEL
fastapi_manage-0.8.0.dist-info/METADATA
fastapi_manage-0.8.0.dist-info/RECORD
