Metadata-Version: 2.1
Name: fastapi-manage
Version: 0.8.0
Summary: FastAPI template generation, database version management tools
Home-page: https://gitee.com/LeanDe/fastapi-manage
License: MIT
Author: lewei_huang
Author-email: auxpd96@163.com
Requires-Python: >=3.6
Classifier: Intended Audience :: Developers
Classifier: License :: OSI Approved :: MIT License
Classifier: Operating System :: OS Independent
Classifier: Programming Language :: Python :: 3
Classifier: Programming Language :: Python :: 3.6
Classifier: Programming Language :: Python :: 3.7
Classifier: Programming Language :: Python :: 3.8
Classifier: Programming Language :: Python :: 3.9
Requires-Dist: Jinja2 (>=2.11.2)
Requires-Dist: PyMySQL (>=0.9.3)
Requires-Dist: SQLAlchemy (>=1.3.20)
Requires-Dist: alembic (>=1.5.6)
Requires-Dist: aredis (>=1.1.8)
Requires-Dist: asgi-ratelimit (>=0.4.0)
Requires-Dist: bcrypt (>=3.2.0)
Requires-Dist: celery (>=5.0.5)
Requires-Dist: configobj (>=5.0.6)
Requires-Dist: cryptography (>=3.3.2,<3.4.0)
Requires-Dist: fastapi (>=0.62.0)
Requires-Dist: gunicorn (>=20.0.4)
Requires-Dist: itsdangerous (>=1.1.0)
Requires-Dist: loguru (>=0.5.3)
Requires-Dist: python-dotenv (>=0.15.0)
Requires-Dist: python-jose (>=3.2.0)
Requires-Dist: python-multipart (>=0.0.5)
Requires-Dist: requests (>=2.25.1)
Requires-Dist: typer (>=0.3.2)
Requires-Dist: uvicorn (>=0.11.8)
Project-URL: Repository, https://gitee.com/LeanDe/fastapi-manage
